CHANGELOG.rst
LICENSE
MANIFEST.in
README.rst
fedmsg_genacls.py
setup.py
fedmsg.d/genacls-example-config.py
fedmsg_genacls.egg-info/PKG-INFO
fedmsg_genacls.egg-info/SOURCES.txt
fedmsg_genacls.egg-info/dependency_links.txt
fedmsg_genacls.egg-info/entry_points.txt
fedmsg_genacls.egg-info/requires.txt
fedmsg_genacls.egg-info/top_level.txt