Metadata-Version: 1.0
Name: fedmsg-genacls
Version: 0.5
Summary: A fedmsg consumer that sets gitosis acls in response to pkgdb messages
Home-page: https://github.com/fedora-infra/fedmsg-genacls
Author: Janez Nemanič and Ralph Bean
Author-email: admin@fedoraproject.org
License: LGPLv2+
Platform: UNKNOWN
